emergingtrajectories/__init__.py
emergingtrajectories/agents.py
emergingtrajectories/chunkers.py
emergingtrajectories/citationagents.py
emergingtrajectories/crawlers.py
emergingtrajectories/facts.py
emergingtrajectories/factsforecaster.py
emergingtrajectories/factsrag.py
emergingtrajectories/factsrag2.py
emergingtrajectories/factsrag3.py
emergingtrajectories/factsragforecaster.py
emergingtrajectories/factsragforecaster2.py
emergingtrajectories/factsragforecaster3.py
emergingtrajectories/knowledge.py
emergingtrajectories/news.py
emergingtrajectories/pdf.py
emergingtrajectories/prompts.py
emergingtrajectories/recursiveagent.py
emergingtrajectories/utils.py
emergingtrajectories-0.2.55.dist-info/LICENSE
emergingtrajectories-0.2.55.dist-info/METADATA
emergingtrajectories-0.2.55.dist-info/WHEEL
emergingtrajectories-0.2.55.dist-info/top_level.txt
emergingtrajectories-0.2.55.dist-info/RECORD
