Metadata-Version: 2.1
Name: emergingtrajectories
Version: 0.2.55
Summary: Open source library for tracking and saving forecasts of political, economic, and social events.
Home-page: UNKNOWN
Author: Wojciech Gryc
Author-email: hello@phaseai.com
License: MIT
Keywords: llm,nlp,ai,social,politics,economics
Platform: UNKNOWN
Classifier: Development Status :: 3 - Alpha
Classifier: Intended Audience :: Developers
Classifier: License :: OSI Approved :: MIT License
Classifier: Programming Language :: Python :: 3
Requires-Python: >=3.10.0
License-File: LICENSE
Requires-Dist: phasellm >=0.0.22
Requires-Dist: Django >=5.0.0
Requires-Dist: python-dotenv >=1.0.0
Requires-Dist: dateparser >=1.2.0
Requires-Dist: pytest-playwright
Requires-Dist: beautifulsoup4
Requires-Dist: chromadb
Requires-Dist: feedparser
Requires-Dist: pypdf
Requires-Dist: faiss-cpu
Requires-Dist: microsoft-bing-newssearch
Requires-Dist: scrapingbee
Requires-Dist: tiktoken
Provides-Extra: docs
Requires-Dist: furo ; extra == 'docs'
Requires-Dist: sphinx >=7.1.2 ; extra == 'docs'
Requires-Dist: myst-parser >=2.0.0 ; extra == 'docs'
Requires-Dist: sphinx-autoapi >=2.1.1 ; extra == 'docs'
Requires-Dist: sphinx-autobuild >=2021.3.14 ; extra == 'docs'
